running_time/__init__.py
running_time/logging/__init__.py
running_time/logging/logmachine.py
running_time/running/__init__.py
running_time/running/runner.py
running_time-0.0.1.dist-info/METADATA
running_time-0.0.1.dist-info/WHEEL
running_time-0.0.1.dist-info/top_level.txt
running_time-0.0.1.dist-info/RECORD
