Metadata-Version: 2.1
Name: running-time
Version: 0.0.1
Summary: Function operation time measurement
Home-page: UNKNOWN
Author: Jose Kim
Author-email: josekim0613@gmail.com
License: UNKNOWN
Platform: UNKNOWN
Classifier: Programming Language :: Python :: 3
Classifier: License :: OSI Approved :: MIT License
Classifier: Operating System :: OS Independent
Requires-Python: >=3.8
